mycalc/calculator.py
hyeongjin-1.0.1.dist-info/METADATA
hyeongjin-1.0.1.dist-info/WHEEL
hyeongjin-1.0.1.dist-info/top_level.txt
hyeongjin-1.0.1.dist-info/RECORD
