Metadata-Version: 2.1
Name: hyeongjin
Version: 1.0.1
Summary: nice calc
Home-page: 
Download-URL: 
Author: hyeongjin
License: UNKNOWN
Platform: UNKNOWN
Classifier: Programming Language :: Python :: 3
